{
  "qb": ["Joe Theismann", "Joe Washington"],
  "rb": ["John Riggins", "Joe Washington", "Clarence Harmon"],
  "wr": ["Art Monk", "Charlie Brown", "Virgil Seay", "Alvin Garrett"],
  "te": ["Don Warren", "Rick Walker", "Clint Didier"],
  "ol": ["Joe Jacoby", "Russ Grimm", "Jeff Bostic", "Mark May", "George Starke"],
  "dl": ["Dexter Manley", "Dave Butz", "Darryl Grant", "Charles Mann"],
  "lb": ["Rich Milot", "Neal Olkewicz", "Monte Coleman"],
  "db": ["Darrell Green", "Vernon Dean", "Mark Murphy", "Tony Peters"],
  "k": ["Mark Moseley"],
  "p": ["Jeff Hayes"],
  "kr": ["Mike Nelms", "Darrell Green"]
}
